antares/tsgen/__init__.py
antares/tsgen/cluster_import.py
antares/tsgen/cluster_parsing.py
antares/tsgen/cluster_resolve.py
antares/tsgen/duration_generator.py
antares/tsgen/main.py
antares/tsgen/mersenne_twister.py
antares/tsgen/py.typed
antares/tsgen/random_generator.py
antares/tsgen/ts_generator.py
antares_timeseries_generation-0.1.9.dist-info/licenses/AUTHORS.txt
antares_timeseries_generation-0.1.9.dist-info/licenses/LICENSE
antares_timeseries_generation-0.1.9.dist-info/METADATA
antares_timeseries_generation-0.1.9.dist-info/WHEEL
antares_timeseries_generation-0.1.9.dist-info/top_level.txt
antares_timeseries_generation-0.1.9.dist-info/RECORD
