Metadata-Version: 2.4
Name: antares-timeseries-generation
Version: 0.1.9
Summary: Timeseries generation library aiming at creating input data for Antares simulator studies.
License: MPL-2.0
Classifier: Development Status :: 4 - Beta
Classifier: License :: OSI Approved :: MIT License
Classifier: License :: OSI Approved :: Mozilla Public License 2.0 (MPL 2.0)
License-File: LICENSE
License-File: AUTHORS.txt
Requires-Dist: numpy
Requires-Dist: pandas
Requires-Dist: PyYAML
Dynamic: license-file
